arcade_intercom_api/__init__.py
arcade_intercom_api/moar/Intercom.json
arcade_intercom_api/moar/openapi.json
arcade_intercom_api/tools/__init__.py
arcade_intercom_api/tools/request_body_schemas.py
arcade_intercom_api/wrapper_tools/AddNoteToContact.json
arcade_intercom_api/wrapper_tools/ArchiveContact.json
arcade_intercom_api/wrapper_tools/AttachCompanyToContact.json
arcade_intercom_api/wrapper_tools/AttachContactToConversation.json
arcade_intercom_api/wrapper_tools/AutoAssignIntercomConversation.json
arcade_intercom_api/wrapper_tools/CancelDataExportJob.json
arcade_intercom_api/wrapper_tools/CheckExportJobStatus.json
arcade_intercom_api/wrapper_tools/ConvertVisitorToUser.json
arcade_intercom_api/wrapper_tools/CreateAdminInitiatedMessage.json
arcade_intercom_api/wrapper_tools/CreateContactConversation.json
arcade_intercom_api/wrapper_tools/CreateDataAttribute.json
arcade_intercom_api/wrapper_tools/CreateEventSummaries.json
arcade_intercom_api/wrapper_tools/CreateHelpCenterCollection.json
arcade_intercom_api/wrapper_tools/CreateHelpCenterSection.json
arcade_intercom_api/wrapper_tools/CreateIntercomArticle.json
arcade_intercom_api/wrapper_tools/CreateIntercomTicket.json
arcade_intercom_api/wrapper_tools/CreateMessageDataExport.json
arcade_intercom_api/wrapper_tools/CreateNewContact.json
arcade_intercom_api/wrapper_tools/CreateNewsItem.json
arcade_intercom_api/wrapper_tools/CreateOrUpdateCompany.json
arcade_intercom_api/wrapper_tools/CreateTicketAttribute.json
arcade_intercom_api/wrapper_tools/CreateTicketType.json
arcade_intercom_api/wrapper_tools/DeflectPhoneCallsToMessenger.json
arcade_intercom_api/wrapper_tools/DeleteCollection.json
arcade_intercom_api/wrapper_tools/DeleteCompany.json
arcade_intercom_api/wrapper_tools/DeleteContact.json
arcade_intercom_api/wrapper_tools/DeleteIntercomArticle.json
arcade_intercom_api/wrapper_tools/DeleteIntercomSection.json
arcade_intercom_api/wrapper_tools/DeleteNewsItem.json
arcade_intercom_api-1.0.0.dist-info/METADATA
arcade_intercom_api-1.0.0.dist-info/WHEEL
arcade_intercom_api-1.0.0.dist-info/entry_points.txt
arcade_intercom_api-1.0.0.dist-info/licenses/LICENSE
arcade_intercom_api-1.0.0.dist-info/RECORD
